irreversibility/__init__.py
irreversibility/exposeTests.py
irreversibility/exposeTestsDiscrete.py
irreversibility/optionalNJIT.py
irreversibility/warningHandling.py
irreversibility/DiscreteMetrics/CostaIndex.py
irreversibility/DiscreteMetrics/DetBalance.py
irreversibility/DiscreteMetrics/Gaspard.py
irreversibility/DiscreteMetrics/__init__.py
irreversibility/Downsampling/Downsampling.py
irreversibility/Downsampling/__init__.py
irreversibility/Manipulation/COP.py
irreversibility/Manipulation/__init__.py
irreversibility/Metrics/BDS.py
irreversibility/Metrics/COP.py
irreversibility/Metrics/Casali.py
irreversibility/Metrics/CostaIndex.py
irreversibility/Metrics/DFK.py
irreversibility/Metrics/Diks.py
irreversibility/Metrics/LocalCC.py
irreversibility/Metrics/MSTrends.py
irreversibility/Metrics/PermPatterns.py
irreversibility/Metrics/Pomeau.py
irreversibility/Metrics/ProductOfPowers.py
irreversibility/Metrics/Ramsey.py
irreversibility/Metrics/Skewness.py
irreversibility/Metrics/TPLength.py
irreversibility/Metrics/TernaryCoding.py
irreversibility/Metrics/VisibilityGraph.py
irreversibility/Metrics/Zumbach.py
irreversibility/Metrics/__init__.py
irreversibility/ParameterOptimisation/Opt_BDS.py
irreversibility/ParameterOptimisation/Opt_COP.py
irreversibility/ParameterOptimisation/Opt_Casali.py
irreversibility/ParameterOptimisation/Opt_CostaIndex.py
irreversibility/ParameterOptimisation/Opt_CostaIndexDiscrete.py
irreversibility/ParameterOptimisation/Opt_DFK.py
irreversibility/ParameterOptimisation/Opt_Diks.py
irreversibility/ParameterOptimisation/Opt_LocalCC.py
irreversibility/ParameterOptimisation/Opt_MSTrends.py
irreversibility/ParameterOptimisation/Opt_PermPatterns.py
irreversibility/ParameterOptimisation/Opt_Pomeau.py
irreversibility/ParameterOptimisation/Opt_Ramsey.py
irreversibility/ParameterOptimisation/Opt_Skewness.py
irreversibility/ParameterOptimisation/Opt_TPLength.py
irreversibility/ParameterOptimisation/Opt_TernaryCoding.py
irreversibility-1.3.0.dist-info/licenses/LICENSE
irreversibility-1.3.0.dist-info/METADATA
irreversibility-1.3.0.dist-info/WHEEL
irreversibility-1.3.0.dist-info/top_level.txt
irreversibility-1.3.0.dist-info/RECORD
