Metadata-Version: 2.4
Name: irreversibility
Version: 1.3.0
Summary: A library for evaluating the time irreversibility of time series
Author-email: Massimiliano Zanin <massimiliano.zanin@gmail.com>
License-Expression: AGPL-3.0-only
Project-URL: Homepage, https://gitlab.com/MZanin/irreversibilitytestslibrary
Project-URL: Issues, https://gitlab.com/MZanin/irreversibilitytestslibrary/issues
Project-URL: Documentation, https://gitlab.com/MZanin/irreversibilitytestslibrary/-/wikis/home
Project-URL: Repository, https://gitlab.com/MZanin/irreversibilitytestslibrary
Project-URL: Changelog, https://gitlab.com/MZanin/irreversibilitytestslibrary/-/wikis/home/Version-History
Keywords: time series,irreversibility,time symmetry,statistical physics
Classifier: Programming Language :: Python :: 3
Classifier: Operating System :: OS Independent
Requires-Python: >=3.11
License-File: LICENSE
Requires-Dist: numpy
Requires-Dist: statsmodels
Requires-Dist: scipy
Provides-Extra: test
Requires-Dist: pytest; extra == "test"
Requires-Dist: pytest-cov; extra == "test"
Requires-Dist: coverage; extra == "test"
Provides-Extra: all
Requires-Dist: irreversibility[lint,test]; extra == "all"
Dynamic: license-file
